tabpfgen/__init__.py
tabpfgen/tabpfgen.py
tabpfgen/tabpfgen_old.py
tabpfgen/visuals.py
tabpfgen-0.1.4.dist-info/licenses/LICENSE
tabpfgen-0.1.4.dist-info/METADATA
tabpfgen-0.1.4.dist-info/WHEEL
tabpfgen-0.1.4.dist-info/top_level.txt
tabpfgen-0.1.4.dist-info/RECORD
