Metadata-Version: 2.4
Name: TabPFGen
Version: 0.1.4
Summary: Synthetic tabular data generation using energy-based modeling and TabPFN
Home-page: https://github.com/sebhaan/TabPFGen
Author: Sebastian Haan
Classifier: License :: OSI Approved :: Apache Software License
Classifier: Programming Language :: Python :: 3
Classifier: Operating System :: OS Independent
Classifier: Topic :: Scientific/Engineering :: Artificial Intelligence
Requires-Python: >=3.10
License-File: LICENSE
Requires-Dist: numpy>=1.26.0
Requires-Dist: torch>=2.5.0
Requires-Dist: scikit-learn==1.5.2
Requires-Dist: matplotlib>=3.10.0
Requires-Dist: scipy>=1.15.0
Requires-Dist: tabpfn>=2.0.1
Requires-Dist: pandas>=2.2.0
Requires-Dist: seaborn>=0.12.0
Dynamic: author
Dynamic: classifier
Dynamic: description
Dynamic: description-content-type
Dynamic: home-page
Dynamic: license-file
Dynamic: requires-dist
Dynamic: requires-python
Dynamic: summary
